{"$schema":"https://json-schema.org/draft/2020-12/schema","type":"object","additionalProperties":false,"required":["schema","run_id","config_hash","task_id","verdict","accepted_at","result_path","notes"],"properties":{"schema":{"const":"apex.kb.semantic-acceptance.v1"},"run_id":{"type":"string"},"config_hash":{"type":"string"},"task_id":{"type":"string"},"verdict":{"enum":["structurally_accepted_pending_independent_semantic_acceptance","semantic_pass","semantic_partial","semantic_fail","insufficient_evidence"]},"accepted_at":{"type":"string"},"result_path":{"type":"string"},"notes":{"type":"array","items":{"type":"string"}}}}
